py_tls/__init__.py
py_tls/__version__.py
py_tls/cffi.py
py_tls/cookies.py
py_tls/exceptions.py
py_tls/response.py
py_tls/sessions.py
py_tls/structures.py
py_tls/async/__init__.py
py_tls/async/session.py
py_tls/dependencies/__init__.py
py_tls/dependencies/tls-client-32.dll
py_tls/dependencies/tls-client-64.dll
py_tls/dependencies/tls-client-arm64.dylib
py_tls/dependencies/tls-client-x86.dylib
py_async_tls-0.1.0.dist-info/LICENSE
py_async_tls-0.1.0.dist-info/METADATA
py_async_tls-0.1.0.dist-info/WHEEL
py_async_tls-0.1.0.dist-info/top_level.txt
py_async_tls-0.1.0.dist-info/RECORD
