Metadata-Version: 2.1
Name: py-async-tls
Version: 0.1.0
Summary: Python TLS client with async support
Author: Tyler Kruer
Author-email: tkruer1@gmail.com
Classifier: Development Status :: 3 - Alpha
Classifier: License :: OSI Approved :: MIT License
Classifier: Programming Language :: Python :: 3.8
Classifier: Environment :: Web Environment
Classifier: Intended Audience :: Developers
Classifier: Natural Language :: English
Classifier: Operating System :: Unix
Classifier: Operating System :: MacOS :: MacOS X
Classifier: Operating System :: Microsoft :: Windows
Classifier: Programming Language :: Python
Classifier: Programming Language :: Python :: 3
Classifier: Topic :: Internet :: WWW/HTTP
Classifier: Topic :: Software Development :: Libraries
License-File: LICENSE
